Metadata-Version: 1.2
Name: pyraii
Version: 1.0.1
Summary: Declerative resource management library for python
Home-page: https://github.com/sasha-tkachev/pyraii
Author: Alexander Tkachev
Author-email: sasha64sasha@gmail.com
License: MIT license
Keywords: pyraii
Platform: UNKNOWN
Classifier: Development Status :: 2 - Pre-Alpha
Classifier: Intended Audience :: Developers
Classifier: License :: OSI Approved :: MIT License
Classifier: Natural Language :: English
Classifier: Programming Language :: Python :: 2
Classifier: Programming Language :: Python :: 2.7
Classifier: Programming Language :: Python :: 3
Classifier: Programming Language :: Python :: 3.5
Classifier: Programming Language :: Python :: 3.6
Classifier: Programming Language :: Python :: 3.7
Requires-Python: >=2.7, !=3.0.*, !=3.1.*, !=3.2.*, !=3.3.*, !=3.4.*
